{
	"class": "Ticket.Ticket",
	"load_arg": {
		"class": "Ticket.TicketWhere",
		"values": [],
		"limit": 250,
		"offset": 0
	},
	"attributes": ["account.id", "account.number", "number", "created", "modified", "subject", "category.name",	"priority.name", "queue.name",
	               "status.name", "source.name", "assignee.name", "subcategory.name", "difficulty", "has_linux_servers",
                   "severity.name", "has_windows_servers", "account.service_level_name","account.support_team.support_territory.code", "queue.id",
                   "assignee.employee_userid", "status.types.name"]
}